[
    {
        "EventID": "7504_0101_devworldbluekillwolfquest_success",
        "GameEventType": "",
        "Level": 1,
        "CreatureType": "Quest",
        "RewardModifier": "",
        "Reward Type": "",
        "UniversalExpAmount": 75,
        "CurrencyReward": 1517,
        "RewardsNotes": "",
        "ItemReward": "QuestRewardArmorT2",
        "ItemRewardQty": "",
        "GearScoreRange": null,
        "CategoricalProgressionId": "",
        "CategoricalProgressionReward": "",
        "TerritoryStanding": 175,
        "FactionReputation": "",
        "FactionInfluenceAmount": "",
        "FactionInfluenceSrc": "",
        "AzothReward": 0,
        "AzothRewardChance": 1,
        "WhisperId": "",
        "AchievementId": "",
        "IgnoreEconomyTracker": "",
        "EntitlementId": "",
        "PVPXP": "",
        "RemoveStatusEffectCategories": "",
        "EmitTelemetry": true
    },
    {
        "EventID": "7505_0101_devworldbluegetcavelootquest_success",
        "GameEventType": "",
        "Level": 1,
        "CreatureType": "Quest",
        "RewardModifier": "",
        "Reward Type": "",
        "UniversalExpAmount": 75,
        "CurrencyReward": 1517,
        "RewardsNotes": "",
        "ItemReward": "2hWarhammerDropT2",
        "ItemRewardQty": "",
        "GearScoreRange": 100,
        "CategoricalProgressionId": "",
        "CategoricalProgressionReward": "",
        "TerritoryStanding": 175,
        "FactionReputation": "",
        "FactionInfluenceAmount": "",
        "FactionInfluenceSrc": "",
        "AzothReward": 0,
        "AzothRewardChance": 1,
        "WhisperId": "",
        "AchievementId": "",
        "IgnoreEconomyTracker": "",
        "EntitlementId": "",
        "PVPXP": "",
        "RemoveStatusEffectCategories": "",
        "EmitTelemetry": true
    }
]
