[
    {
        "ExpansionId": "None",
        "DisplayName": "New World",
        "Icon": "lyshineui/images/icons/newworld/logoNewWorldCondensed",
        "MaxDisplayLevel": 60,
        "MaxCraftGS": 625,
        "MaxEquipGS": 625,
        "MaxTradeskillLevel": 200,
        "EntitlementId": ""
    },
    {
        "ExpansionId": "Expansion2023",
        "DisplayName": "Rise of the Angry Earth",
        "Icon": "lyshineui/images/icons/newworld/icon_expansion_1",
        "MaxDisplayLevel": 65,
        "MaxCraftGS": 700,
        "MaxEquipGS": 700,
        "MaxTradeskillLevel": 250,
        "EntitlementId": "Ent_Xpack_RiseOfTheAngryEarth_Owner"
    }
]
